{
  "owner": "HelixCipher",
  "totalRepos": 32,
  "totalClones": 1693,
  "totalUniques": 947,
  "totalCombined": 2640,
  "downloads14d": 0,
  "downloadsTotal": 0,
  "repos": [
    {
      "name": "clone-sweeper",
      "clones": 1144,
      "uniques": 485,
      "combined": 1629
    },
    {
      "name": "HelixCipher",
      "clones": 109,
      "uniques": 82,
      "combined": 191
    },
    {
      "name": "pages",
      "clones": 47,
      "uniques": 31,
      "combined": 78
    },
    {
      "name": "project-jackheart",
      "clones": 45,
      "uniques": 40,
      "combined": 85
    },
    {
      "name": "digit-classifier-api",
      "clones": 31,
      "uniques": 30,
      "combined": 61
    },
    {
      "name": "machine-learning",
      "clones": 25,
      "uniques": 19,
      "combined": 44
    }
  ]
}